{
  "objects": [
    {
      "browseName": "CH_M52_ACM2",
      "displayName": "Черкассы 'АЗОТ' цех M5/2 ACM2",
      "type": "object",
      "view": {
        "tab1": [
          { "name": "Концентрация N2O", "items": ["N2O"] },
          { "name": "Выхлоп. Газы", "items": ["VSG"] },
          { "name": "Коррекция N2O", "items": ["N2O_CORR"] },
          { "name": "Коррекция VSG", "items": ["VSG_CORR"] },
          { "name": "F105 Работает", "items": ["HNO3"] }
        ]
      }
    }
  ],
  "variables": [
    {
      "browseName": "CH_M52_ACM2::ValueFromFile",
      "displayName": "Значения из файла для CH_M52_ACM2",
      "ownerName": "CH_M52_ACM2",
      "type": "variable.simple",
      "dataType": "String",
      "hist": true,
      "group": true,
      "variableGetType": "valueFromSource",
      "getter": "acmDayValueFromPath",
      "getterParams": {
        "path": "//192.168.3.5/www_m5/day_reports/m5-2/ACM/14AGR/"
      }
    }
  ],
  "groups": [
    {
      "browseName": "CH_M52_ACM2::57N2O:57QN2O_H01",
      "aliasName": "57QN2O_H01",
      "displayName": "57QN2O_H01",
      "ownerName": "CH_M52_ACM2",
      "ownerGroup": "CH_M52_ACM2::ValueFromFile",
      "type": "variable.analog",
      "dataType": "Double",
      "hist": true,
      "variableGetType": "valueFromSource",
      "getter": "plugForVariable",
      "valueParams": {
        "engineeringUnitsRange": {
          "low": 0,
          "high": 2000
        },
        "engineeringUnits": "milligram_per_cubic_metre"
      },
      "description": "Концентрация N2O (Q N2O)"
    },
    {
      "browseName": "CH_M52_ACM2::57N2O:57QN2O_H02",
      "aliasName": "57QN2O_H02",
      "displayName": "57QN2O_H02",
      "ownerName": "CH_M52_ACM2",
      "ownerGroup": "CH_M52_ACM2::ValueFromFile",
      "type": "variable.analog",
      "dataType": "Double",
      "hist": true,
      "variableGetType": "valueFromSource",
      "getter": "plugForVariable",
      "valueParams": {
        "engineeringUnitsRange": {
          "low": 0,
          "high": 2000
        },
        "engineeringUnits": "milligram_per_cubic_metre"
      },
      "description": "Концентрация N2O (Q N2O)"
    },
    {
      "browseName": "CH_M52_ACM2::57N2O:57QN2O_H03",
      "aliasName": "57QN2O_H03",
      "displayName": "57QN2O_H03",
      "ownerName": "CH_M52_ACM2",
      "ownerGroup": "CH_M52_ACM2::ValueFromFile",
      "type": "variable.analog",
      "dataType": "Double",
      "hist": true,
      "variableGetType": "valueFromSource",
      "getter": "plugForVariable",
      "valueParams": {
        "engineeringUnitsRange": {
          "low": 0,
          "high": 2000
        },
        "engineeringUnits": "milligram_per_cubic_metre"
      },
      "description": "Концентрация N2O (Q N2O)"
    },
    {
      "browseName": "CH_M52_ACM2::57N2O:57QN2O_H04",
      "aliasName": "57QN2O_H04",
      "displayName": "57QN2O_H04",
      "ownerName": "CH_M52_ACM2",
      "ownerGroup": "CH_M52_ACM2::ValueFromFile",
      "type": "variable.analog",
      "dataType": "Double",
      "hist": true,
      "variableGetType": "valueFromSource",
      "getter": "plugForVariable",
      "valueParams": {
        "engineeringUnitsRange": {
          "low": 0,
          "high": 2000
        },
        "engineeringUnits": "milligram_per_cubic_metre"
      },
      "description": "Концентрация N2O (Q N2O)"
    },
    {
      "browseName": "CH_M52_ACM2::57N2O:57QN2O_H05",
      "aliasName": "57QN2O_H05",
      "displayName": "57QN2O_H05",
      "ownerName": "CH_M52_ACM2",
      "ownerGroup": "CH_M52_ACM2::ValueFromFile",
      "type": "variable.analog",
      "dataType": "Double",
      "hist": true,
      "variableGetType": "valueFromSource",
      "getter": "plugForVariable",
      "valueParams": {
        "engineeringUnitsRange": {
          "low": 0,
          "high": 2000
        },
        "engineeringUnits": "milligram_per_cubic_metre"
      },
      "description": "Концентрация N2O (Q N2O)"
    },
    {
      "browseName": "CH_M52_ACM2::57N2O:57QN2O_H06",
      "aliasName": "57QN2O_H06",
      "displayName": "57QN2O_H06",
      "ownerName": "CH_M52_ACM2",
      "ownerGroup": "CH_M52_ACM2::ValueFromFile",
      "type": "variable.analog",
      "dataType": "Double",
      "hist": true,
      "variableGetType": "valueFromSource",
      "getter": "plugForVariable",
      "valueParams": {
        "engineeringUnitsRange": {
          "low": 0,
          "high": 2000
        },
        "engineeringUnits": "milligram_per_cubic_metre"
      },
      "description": "Концентрация N2O (Q N2O)"
    },
    {
      "browseName": "CH_M52_ACM2::57N2O:57QN2O_H07",
      "aliasName": "57QN2O_H07",
      "displayName": "57QN2O_H07",
      "ownerName": "CH_M52_ACM2",
      "ownerGroup": "CH_M52_ACM2::ValueFromFile",
      "type": "variable.analog",
      "dataType": "Double",
      "hist": true,
      "variableGetType": "valueFromSource",
      "getter": "plugForVariable",
      "valueParams": {
        "engineeringUnitsRange": {
          "low": 0,
          "high": 2000
        },
        "engineeringUnits": "milligram_per_cubic_metre"
      },
      "description": "Концентрация N2O (Q N2O)"
    },
    {
      "browseName": "CH_M52_ACM2::57N2O:57QN2O_H08",
      "aliasName": "57QN2O_H08",
      "displayName": "57QN2O_H08",
      "ownerName": "CH_M52_ACM2",
      "ownerGroup": "CH_M52_ACM2::ValueFromFile",
      "type": "variable.analog",
      "dataType": "Double",
      "hist": true,
      "variableGetType": "valueFromSource",
      "getter": "plugForVariable",
      "valueParams": {
        "engineeringUnitsRange": {
          "low": 0,
          "high": 2000
        },
        "engineeringUnits": "milligram_per_cubic_metre"
      },
      "description": "Концентрация N2O (Q N2O)"
    },
    {
      "browseName": "CH_M52_ACM2::57N2O:57QN2O_H09",
      "aliasName": "57QN2O_H09",
      "displayName": "57QN2O_H09",
      "ownerName": "CH_M52_ACM2",
      "ownerGroup": "CH_M52_ACM2::ValueFromFile",
      "type": "variable.analog",
      "dataType": "Double",
      "hist": true,
      "variableGetType": "valueFromSource",
      "getter": "plugForVariable",
      "valueParams": {
        "engineeringUnitsRange": {
          "low": 0,
          "high": 2000
        },
        "engineeringUnits": "milligram_per_cubic_metre"
      },
      "description": "Концентрация N2O (Q N2O)"
    },
    {
      "browseName": "CH_M52_ACM2::57N2O:57QN2O_H10",
      "aliasName": "57QN2O_H10",
      "displayName": "57QN2O_H10",
      "ownerName": "CH_M52_ACM2",
      "ownerGroup": "CH_M52_ACM2::ValueFromFile",
      "type": "variable.analog",
      "dataType": "Double",
      "hist": true,
      "variableGetType": "valueFromSource",
      "getter": "plugForVariable",
      "valueParams": {
        "engineeringUnitsRange": {
          "low": 0,
          "high": 2000
        },
        "engineeringUnits": "milligram_per_cubic_metre"
      },
      "description": "Концентрация N2O (Q N2O)"
    },
    {
      "browseName": "CH_M52_ACM2::57N2O:57QN2O_H11",
      "aliasName": "57QN2O_H11",
      "displayName": "57QN2O_H11",
      "ownerName": "CH_M52_ACM2",
      "ownerGroup": "CH_M52_ACM2::ValueFromFile",
      "type": "variable.analog",
      "dataType": "Double",
      "hist": true,
      "variableGetType": "valueFromSource",
      "getter": "plugForVariable",
      "valueParams": {
        "engineeringUnitsRange": {
          "low": 0,
          "high": 2000
        },
        "engineeringUnits": "milligram_per_cubic_metre"
      },
      "description": "Концентрация N2O (Q N2O)"
    },
    {
      "browseName": "CH_M52_ACM2::57N2O:57QN2O_H12",
      "aliasName": "57QN2O_H12",
      "displayName": "57QN2O_H12",
      "ownerName": "CH_M52_ACM2",
      "ownerGroup": "CH_M52_ACM2::ValueFromFile",
      "type": "variable.analog",
      "dataType": "Double",
      "hist": true,
      "variableGetType": "valueFromSource",
      "getter": "plugForVariable",
      "valueParams": {
        "engineeringUnitsRange": {
          "low": 0,
          "high": 2000
        },
        "engineeringUnits": "milligram_per_cubic_metre"
      },
      "description": "Концентрация N2O (Q N2O)"
    },
    {
      "browseName": "CH_M52_ACM2::57N2O:57QN2O_H13",
      "aliasName": "57QN2O_H13",
      "displayName": "57QN2O_H13",
      "ownerName": "CH_M52_ACM2",
      "ownerGroup": "CH_M52_ACM2::ValueFromFile",
      "type": "variable.analog",
      "dataType": "Double",
      "hist": true,
      "variableGetType": "valueFromSource",
      "getter": "plugForVariable",
      "valueParams": {
        "engineeringUnitsRange": {
          "low": 0,
          "high": 2000
        },
        "engineeringUnits": "milligram_per_cubic_metre"
      },
      "description": "Концентрация N2O (Q N2O)"
    },
    {
      "browseName": "CH_M52_ACM2::57N2O:57QN2O_H14",
      "aliasName": "57QN2O_H14",
      "displayName": "57QN2O_H14",
      "ownerName": "CH_M52_ACM2",
      "ownerGroup": "CH_M52_ACM2::ValueFromFile",
      "type": "variable.analog",
      "dataType": "Double",
      "hist": true,
      "variableGetType": "valueFromSource",
      "getter": "plugForVariable",
      "valueParams": {
        "engineeringUnitsRange": {
          "low": 0,
          "high": 2000
        },
        "engineeringUnits": "milligram_per_cubic_metre"
      },
      "description": "Концентрация N2O (Q N2O)"
    },
    {
      "browseName": "CH_M52_ACM2::57N2O:57QN2O_H15",
      "aliasName": "57QN2O_H15",
      "displayName": "57QN2O_H15",
      "ownerName": "CH_M52_ACM2",
      "ownerGroup": "CH_M52_ACM2::ValueFromFile",
      "type": "variable.analog",
      "dataType": "Double",
      "hist": true,
      "variableGetType": "valueFromSource",
      "getter": "plugForVariable",
      "valueParams": {
        "engineeringUnitsRange": {
          "low": 0,
          "high": 2000
        },
        "engineeringUnits": "milligram_per_cubic_metre"
      },
      "description": "Концентрация N2O (Q N2O)"
    },
    {
      "browseName": "CH_M52_ACM2::57N2O:57QN2O_H16",
      "aliasName": "57QN2O_H16",
      "displayName": "57QN2O_H16",
      "ownerName": "CH_M52_ACM2",
      "ownerGroup": "CH_M52_ACM2::ValueFromFile",
      "type": "variable.analog",
      "dataType": "Double",
      "hist": true,
      "variableGetType": "valueFromSource",
      "getter": "plugForVariable",
      "valueParams": {
        "engineeringUnitsRange": {
          "low": 0,
          "high": 2000
        },
        "engineeringUnits": "milligram_per_cubic_metre"
      },
      "description": "Концентрация N2O (Q N2O)"
    },
    {
      "browseName": "CH_M52_ACM2::57N2O:57QN2O_H17",
      "aliasName": "57QN2O_H17",
      "displayName": "57QN2O_H17",
      "ownerName": "CH_M52_ACM2",
      "ownerGroup": "CH_M52_ACM2::ValueFromFile",
      "type": "variable.analog",
      "dataType": "Double",
      "hist": true,
      "variableGetType": "valueFromSource",
      "getter": "plugForVariable",
      "valueParams": {
        "engineeringUnitsRange": {
          "low": 0,
          "high": 2000
        },
        "engineeringUnits": "milligram_per_cubic_metre"
      },
      "description": "Концентрация N2O (Q N2O)"
    },
    {
      "browseName": "CH_M52_ACM2::57N2O:57QN2O_H18",
      "aliasName": "57QN2O_H18",
      "displayName": "57QN2O_H18",
      "ownerName": "CH_M52_ACM2",
      "ownerGroup": "CH_M52_ACM2::ValueFromFile",
      "type": "variable.analog",
      "dataType": "Double",
      "hist": true,
      "variableGetType": "valueFromSource",
      "getter": "plugForVariable",
      "valueParams": {
        "engineeringUnitsRange": {
          "low": 0,
          "high": 2000
        },
        "engineeringUnits": "milligram_per_cubic_metre"
      },
      "description": "Концентрация N2O (Q N2O)"
    },
    {
      "browseName": "CH_M52_ACM2::57N2O:57QN2O_H19",
      "aliasName": "57QN2O_H19",
      "displayName": "57QN2O_H19",
      "ownerName": "CH_M52_ACM2",
      "ownerGroup": "CH_M52_ACM2::ValueFromFile",
      "type": "variable.analog",
      "dataType": "Double",
      "hist": true,
      "variableGetType": "valueFromSource",
      "getter": "plugForVariable",
      "valueParams": {
        "engineeringUnitsRange": {
          "low": 0,
          "high": 2000
        },
        "engineeringUnits": "milligram_per_cubic_metre"
      },
      "description": "Концентрация N2O (Q N2O)"
    },
    {
      "browseName": "CH_M52_ACM2::57N2O:57QN2O_H20",
      "aliasName": "57QN2O_H20",
      "displayName": "57QN2O_H20",
      "ownerName": "CH_M52_ACM2",
      "ownerGroup": "CH_M52_ACM2::ValueFromFile",
      "type": "variable.analog",
      "dataType": "Double",
      "hist": true,
      "variableGetType": "valueFromSource",
      "getter": "plugForVariable",
      "valueParams": {
        "engineeringUnitsRange": {
          "low": 0,
          "high": 2000
        },
        "engineeringUnits": "milligram_per_cubic_metre"
      },
      "description": "Концентрация N2O (Q N2O)"
    },
    {
      "browseName": "CH_M52_ACM2::57N2O:57QN2O_H21",
      "aliasName": "57QN2O_H21",
      "displayName": "57QN2O_H21",
      "ownerName": "CH_M52_ACM2",
      "ownerGroup": "CH_M52_ACM2::ValueFromFile",
      "type": "variable.analog",
      "dataType": "Double",
      "hist": true,
      "variableGetType": "valueFromSource",
      "getter": "plugForVariable",
      "valueParams": {
        "engineeringUnitsRange": {
          "low": 0,
          "high": 2000
        },
        "engineeringUnits": "milligram_per_cubic_metre"
      },
      "description": "Концентрация N2O (Q N2O)"
    },
    {
      "browseName": "CH_M52_ACM2::57N2O:57QN2O_H22",
      "aliasName": "57QN2O_H22",
      "displayName": "57QN2O_H22",
      "ownerName": "CH_M52_ACM2",
      "ownerGroup": "CH_M52_ACM2::ValueFromFile",
      "type": "variable.analog",
      "dataType": "Double",
      "hist": true,
      "variableGetType": "valueFromSource",
      "getter": "plugForVariable",
      "valueParams": {
        "engineeringUnitsRange": {
          "low": 0,
          "high": 2000
        },
        "engineeringUnits": "milligram_per_cubic_metre"
      },
      "description": "Концентрация N2O (Q N2O)"
    },
    {
      "browseName": "CH_M52_ACM2::57N2O:57QN2O_H23",
      "aliasName": "57QN2O_H23",
      "displayName": "57QN2O_H23",
      "ownerName": "CH_M52_ACM2",
      "ownerGroup": "CH_M52_ACM2::ValueFromFile",
      "type": "variable.analog",
      "dataType": "Double",
      "hist": true,
      "variableGetType": "valueFromSource",
      "getter": "plugForVariable",
      "valueParams": {
        "engineeringUnitsRange": {
          "low": 0,
          "high": 2000
        },
        "engineeringUnits": "milligram_per_cubic_metre"
      },
      "description": "Концентрация N2O (Q N2O)"
    },
    {
      "browseName": "CH_M52_ACM2::57N2O:57QN2O_H24",
      "aliasName": "57QN2O_H24",
      "displayName": "57QN2O_H24",
      "ownerName": "CH_M52_ACM2",
      "ownerGroup": "CH_M52_ACM2::ValueFromFile",
      "type": "variable.analog",
      "dataType": "Double",
      "hist": true,
      "variableGetType": "valueFromSource",
      "getter": "plugForVariable",
      "valueParams": {
        "engineeringUnitsRange": {
          "low": 0,
          "high": 2000
        },
        "engineeringUnits": "milligram_per_cubic_metre"
      },
      "description": "Концентрация N2O (Q N2O)"
    },
    {
      "browseName": "CH_M52_ACM2::57VSG:57FVSG_H01",
      "aliasName": "57FVSG_H01",
      "displayName": "57FVSG_H01",
      "ownerName": "CH_M52_ACM2",
      "ownerGroup": "CH_M52_ACM2::ValueFromFile",
      "type": "variable.analog",
      "dataType": "Double",
      "hist": true,
      "variableGetType": "valueFromSource",
      "getter": "plugForVariable",
      "valueParams": {
        "engineeringUnitsRange": {
          "low": 0,
          "high": 900000
        },
        "engineeringUnits": "cubic_metre_per_hour"
      },
      "description": "Расход выхл. газов (F VSG)"
    },
    {
      "browseName": "CH_M52_ACM2::57VSG:57FVSG_H02",
      "aliasName": "57FVSG_H02",
      "displayName": "57FVSG_H02",
      "ownerName": "CH_M52_ACM2",
      "ownerGroup": "CH_M52_ACM2::ValueFromFile",
      "type": "variable.analog",
      "dataType": "Double",
      "hist": true,
      "variableGetType": "valueFromSource",
      "getter": "plugForVariable",
      "valueParams": {
        "engineeringUnitsRange": {
          "low": 0,
          "high": 900000
        },
        "engineeringUnits": "cubic_metre_per_hour"
      },
      "description": "Расход выхл. газов (F VSG)"
    },
    {
      "browseName": "CH_M52_ACM2::57VSG:57FVSG_H03",
      "aliasName": "57FVSG_H03",
      "displayName": "57FVSG_H03",
      "ownerName": "CH_M52_ACM2",
      "ownerGroup": "CH_M52_ACM2::ValueFromFile",
      "type": "variable.analog",
      "dataType": "Double",
      "hist": true,
      "variableGetType": "valueFromSource",
      "getter": "plugForVariable",
      "valueParams": {
        "engineeringUnitsRange": {
          "low": 0,
          "high": 900000
        },
        "engineeringUnits": "cubic_metre_per_hour"
      },
      "description": "Расход выхл. газов (F VSG)"
    },
    {
      "browseName": "CH_M52_ACM2::57VSG:57FVSG_H04",
      "aliasName": "57FVSG_H04",
      "displayName": "57FVSG_H04",
      "ownerName": "CH_M52_ACM2",
      "ownerGroup": "CH_M52_ACM2::ValueFromFile",
      "type": "variable.analog",
      "dataType": "Double",
      "hist": true,
      "variableGetType": "valueFromSource",
      "getter": "plugForVariable",
      "valueParams": {
        "engineeringUnitsRange": {
          "low": 0,
          "high": 900000
        },
        "engineeringUnits": "cubic_metre_per_hour"
      },
      "description": "Расход выхл. газов (F VSG)"
    },
    {
      "browseName": "CH_M52_ACM2::57VSG:57FVSG_H05",
      "aliasName": "57FVSG_H05",
      "displayName": "57FVSG_H05",
      "ownerName": "CH_M52_ACM2",
      "ownerGroup": "CH_M52_ACM2::ValueFromFile",
      "type": "variable.analog",
      "dataType": "Double",
      "hist": true,
      "variableGetType": "valueFromSource",
      "getter": "plugForVariable",
      "valueParams": {
        "engineeringUnitsRange": {
          "low": 0,
          "high": 900000
        },
        "engineeringUnits": "cubic_metre_per_hour"
      },
      "description": "Расход выхл. газов (F VSG)"
    },
    {
      "browseName": "CH_M52_ACM2::57VSG:57FVSG_H06",
      "aliasName": "57FVSG_H06",
      "displayName": "57FVSG_H06",
      "ownerName": "CH_M52_ACM2",
      "ownerGroup": "CH_M52_ACM2::ValueFromFile",
      "type": "variable.analog",
      "dataType": "Double",
      "hist": true,
      "variableGetType": "valueFromSource",
      "getter": "plugForVariable",
      "valueParams": {
        "engineeringUnitsRange": {
          "low": 0,
          "high": 900000
        },
        "engineeringUnits": "cubic_metre_per_hour"
      },
      "description": "Расход выхл. газов (F VSG)"
    },
    {
      "browseName": "CH_M52_ACM2::57VSG:57FVSG_H07",
      "aliasName": "57FVSG_H07",
      "displayName": "57FVSG_H07",
      "ownerName": "CH_M52_ACM2",
      "ownerGroup": "CH_M52_ACM2::ValueFromFile",
      "type": "variable.analog",
      "dataType": "Double",
      "hist": true,
      "variableGetType": "valueFromSource",
      "getter": "plugForVariable",
      "valueParams": {
        "engineeringUnitsRange": {
          "low": 0,
          "high": 900000
        },
        "engineeringUnits": "cubic_metre_per_hour"
      },
      "description": "Расход выхл. газов (F VSG)"
    },
    {
      "browseName": "CH_M52_ACM2::57VSG:57FVSG_H08",
      "aliasName": "57FVSG_H08",
      "displayName": "57FVSG_H08",
      "ownerName": "CH_M52_ACM2",
      "ownerGroup": "CH_M52_ACM2::ValueFromFile",
      "type": "variable.analog",
      "dataType": "Double",
      "hist": true,
      "variableGetType": "valueFromSource",
      "getter": "plugForVariable",
      "valueParams": {
        "engineeringUnitsRange": {
          "low": 0,
          "high": 900000
        },
        "engineeringUnits": "cubic_metre_per_hour"
      },
      "description": "Расход выхл. газов (F VSG)"
    },
    {
      "browseName": "CH_M52_ACM2::57VSG:57FVSG_H09",
      "aliasName": "57FVSG_H09",
      "displayName": "57FVSG_H09",
      "ownerName": "CH_M52_ACM2",
      "ownerGroup": "CH_M52_ACM2::ValueFromFile",
      "type": "variable.analog",
      "dataType": "Double",
      "hist": true,
      "variableGetType": "valueFromSource",
      "getter": "plugForVariable",
      "valueParams": {
        "engineeringUnitsRange": {
          "low": 0,
          "high": 900000
        },
        "engineeringUnits": "cubic_metre_per_hour"
      },
      "description": "Расход выхл. газов (F VSG)"
    },
    {
      "browseName": "CH_M52_ACM2::57VSG:57FVSG_H10",
      "aliasName": "57FVSG_H10",
      "displayName": "57FVSG_H10",
      "ownerName": "CH_M52_ACM2",
      "ownerGroup": "CH_M52_ACM2::ValueFromFile",
      "type": "variable.analog",
      "dataType": "Double",
      "hist": true,
      "variableGetType": "valueFromSource",
      "getter": "plugForVariable",
      "valueParams": {
        "engineeringUnitsRange": {
          "low": 0,
          "high": 900000
        },
        "engineeringUnits": "cubic_metre_per_hour"
      },
      "description": "Расход выхл. газов (F VSG)"
    },
    {
      "browseName": "CH_M52_ACM2::57VSG:57FVSG_H11",
      "aliasName": "57FVSG_H11",
      "displayName": "57FVSG_H11",
      "ownerName": "CH_M52_ACM2",
      "ownerGroup": "CH_M52_ACM2::ValueFromFile",
      "type": "variable.analog",
      "dataType": "Double",
      "hist": true,
      "variableGetType": "valueFromSource",
      "getter": "plugForVariable",
      "valueParams": {
        "engineeringUnitsRange": {
          "low": 0,
          "high": 900000
        },
        "engineeringUnits": "cubic_metre_per_hour"
      },
      "description": "Расход выхл. газов (F VSG)"
    },
    {
      "browseName": "CH_M52_ACM2::57VSG:57FVSG_H12",
      "aliasName": "57FVSG_H12",
      "displayName": "57FVSG_H12",
      "ownerName": "CH_M52_ACM2",
      "ownerGroup": "CH_M52_ACM2::ValueFromFile",
      "type": "variable.analog",
      "dataType": "Double",
      "hist": true,
      "variableGetType": "valueFromSource",
      "getter": "plugForVariable",
      "valueParams": {
        "engineeringUnitsRange": {
          "low": 0,
          "high": 900000
        },
        "engineeringUnits": "cubic_metre_per_hour"
      },
      "description": "Расход выхл. газов (F VSG)"
    },
    {
      "browseName": "CH_M52_ACM2::57VSG:57FVSG_H13",
      "aliasName": "57FVSG_H13",
      "displayName": "57FVSG_H13",
      "ownerName": "CH_M52_ACM2",
      "ownerGroup": "CH_M52_ACM2::ValueFromFile",
      "type": "variable.analog",
      "dataType": "Double",
      "hist": true,
      "variableGetType": "valueFromSource",
      "getter": "plugForVariable",
      "valueParams": {
        "engineeringUnitsRange": {
          "low": 0,
          "high": 900000
        },
        "engineeringUnits": "cubic_metre_per_hour"
      },
      "description": "Расход выхл. газов (F VSG)"
    },
    {
      "browseName": "CH_M52_ACM2::57VSG:57FVSG_H14",
      "aliasName": "57FVSG_H14",
      "displayName": "57FVSG_H14",
      "ownerName": "CH_M52_ACM2",
      "ownerGroup": "CH_M52_ACM2::ValueFromFile",
      "type": "variable.analog",
      "dataType": "Double",
      "hist": true,
      "variableGetType": "valueFromSource",
      "getter": "plugForVariable",
      "valueParams": {
        "engineeringUnitsRange": {
          "low": 0,
          "high": 900000
        },
        "engineeringUnits": "cubic_metre_per_hour"
      },
      "description": "Расход выхл. газов (F VSG)"
    },
    {
      "browseName": "CH_M52_ACM2::57VSG:57FVSG_H15",
      "aliasName": "57FVSG_H15",
      "displayName": "57FVSG_H15",
      "ownerName": "CH_M52_ACM2",
      "ownerGroup": "CH_M52_ACM2::ValueFromFile",
      "type": "variable.analog",
      "dataType": "Double",
      "hist": true,
      "variableGetType": "valueFromSource",
      "getter": "plugForVariable",
      "valueParams": {
        "engineeringUnitsRange": {
          "low": 0,
          "high": 900000
        },
        "engineeringUnits": "cubic_metre_per_hour"
      },
      "description": "Расход выхл. газов (F VSG)"
    },
    {
      "browseName": "CH_M52_ACM2::57VSG:57FVSG_H16",
      "aliasName": "57FVSG_H16",
      "displayName": "57FVSG_H16",
      "ownerName": "CH_M52_ACM2",
      "ownerGroup": "CH_M52_ACM2::ValueFromFile",
      "type": "variable.analog",
      "dataType": "Double",
      "hist": true,
      "variableGetType": "valueFromSource",
      "getter": "plugForVariable",
      "valueParams": {
        "engineeringUnitsRange": {
          "low": 0,
          "high": 900000
        },
        "engineeringUnits": "cubic_metre_per_hour"
      },
      "description": "Расход выхл. газов (F VSG)"
    },
    {
      "browseName": "CH_M52_ACM2::57VSG:57FVSG_H17",
      "aliasName": "57FVSG_H17",
      "displayName": "57FVSG_H17",
      "ownerName": "CH_M52_ACM2",
      "ownerGroup": "CH_M52_ACM2::ValueFromFile",
      "type": "variable.analog",
      "dataType": "Double",
      "hist": true,
      "variableGetType": "valueFromSource",
      "getter": "plugForVariable",
      "valueParams": {
        "engineeringUnitsRange": {
          "low": 0,
          "high": 900000
        },
        "engineeringUnits": "cubic_metre_per_hour"
      },
      "description": "Расход выхл. газов (F VSG)"
    },
    {
      "browseName": "CH_M52_ACM2::57VSG:57FVSG_H18",
      "aliasName": "57FVSG_H18",
      "displayName": "57FVSG_H18",
      "ownerName": "CH_M52_ACM2",
      "ownerGroup": "CH_M52_ACM2::ValueFromFile",
      "type": "variable.analog",
      "dataType": "Double",
      "hist": true,
      "variableGetType": "valueFromSource",
      "getter": "plugForVariable",
      "valueParams": {
        "engineeringUnitsRange": {
          "low": 0,
          "high": 900000
        },
        "engineeringUnits": "cubic_metre_per_hour"
      },
      "description": "Расход выхл. газов (F VSG)"
    },
    {
      "browseName": "CH_M52_ACM2::57VSG:57FVSG_H19",
      "aliasName": "57FVSG_H19",
      "displayName": "57FVSG_H19",
      "ownerName": "CH_M52_ACM2",
      "ownerGroup": "CH_M52_ACM2::ValueFromFile",
      "type": "variable.analog",
      "dataType": "Double",
      "hist": true,
      "variableGetType": "valueFromSource",
      "getter": "plugForVariable",
      "valueParams": {
        "engineeringUnitsRange": {
          "low": 0,
          "high": 900000
        },
        "engineeringUnits": "cubic_metre_per_hour"
      },
      "description": "Расход выхл. газов (F VSG)"
    },
    {
      "browseName": "CH_M52_ACM2::57VSG:57FVSG_H20",
      "aliasName": "57FVSG_H20",
      "displayName": "57FVSG_H20",
      "ownerName": "CH_M52_ACM2",
      "ownerGroup": "CH_M52_ACM2::ValueFromFile",
      "type": "variable.analog",
      "dataType": "Double",
      "hist": true,
      "variableGetType": "valueFromSource",
      "getter": "plugForVariable",
      "valueParams": {
        "engineeringUnitsRange": {
          "low": 0,
          "high": 900000
        },
        "engineeringUnits": "cubic_metre_per_hour"
      },
      "description": "Расход выхл. газов (F VSG)"
    },
    {
      "browseName": "CH_M52_ACM2::57VSG:57FVSG_H21",
      "aliasName": "57FVSG_H21",
      "displayName": "57FVSG_H21",
      "ownerName": "CH_M52_ACM2",
      "ownerGroup": "CH_M52_ACM2::ValueFromFile",
      "type": "variable.analog",
      "dataType": "Double",
      "hist": true,
      "variableGetType": "valueFromSource",
      "getter": "plugForVariable",
      "valueParams": {
        "engineeringUnitsRange": {
          "low": 0,
          "high": 900000
        },
        "engineeringUnits": "cubic_metre_per_hour"
      },
      "description": "Расход выхл. газов (F VSG)"
    },
    {
      "browseName": "CH_M52_ACM2::57VSG:57FVSG_H22",
      "aliasName": "57FVSG_H22",
      "displayName": "57FVSG_H22",
      "ownerName": "CH_M52_ACM2",
      "ownerGroup": "CH_M52_ACM2::ValueFromFile",
      "type": "variable.analog",
      "dataType": "Double",
      "hist": true,
      "variableGetType": "valueFromSource",
      "getter": "plugForVariable",
      "valueParams": {
        "engineeringUnitsRange": {
          "low": 0,
          "high": 900000
        },
        "engineeringUnits": "cubic_metre_per_hour"
      },
      "description": "Расход выхл. газов (F VSG)"
    },
    {
      "browseName": "CH_M52_ACM2::57VSG:57FVSG_H23",
      "aliasName": "57FVSG_H23",
      "displayName": "57FVSG_H23",
      "ownerName": "CH_M52_ACM2",
      "ownerGroup": "CH_M52_ACM2::ValueFromFile",
      "type": "variable.analog",
      "dataType": "Double",
      "hist": true,
      "variableGetType": "valueFromSource",
      "getter": "plugForVariable",
      "valueParams": {
        "engineeringUnitsRange": {
          "low": 0,
          "high": 900000
        },
        "engineeringUnits": "cubic_metre_per_hour"
      },
      "description": "Расход выхл. газов (F VSG)"
    },
    {
      "browseName": "CH_M52_ACM2::57VSG:57FVSG_H24",
      "aliasName": "57FVSG_H24",
      "displayName": "57FVSG_H24",
      "ownerName": "CH_M52_ACM2",
      "ownerGroup": "CH_M52_ACM2::ValueFromFile",
      "type": "variable.analog",
      "dataType": "Double",
      "hist": true,
      "variableGetType": "valueFromSource",
      "getter": "plugForVariable",
      "valueParams": {
        "engineeringUnitsRange": {
          "low": 0,
          "high": 900000
        },
        "engineeringUnits": "cubic_metre_per_hour"
      },
      "description": "Расход выхл. газов (F VSG)"
    },
    {
      "browseName": "CH_M52_ACM2::57N2O:57QN2O_CORR_H01",
      "aliasName": "57QN2O_CORR_H01",
      "displayName": "57QN2O_CORR_H01",
      "ownerName": "CH_M52_ACM2",
      "ownerGroup": "CH_M52_ACM2::ValueFromFile",
      "type": "variable.analog",
      "dataType": "Double",
      "hist": true,
      "variableGetType": "valueFromSource",
      "getter": "plugForVariable",
      "valueParams": {
        "engineeringUnitsRange": {
          "low": 0,
          "high": 2000
        },
        "engineeringUnits": "milligram_per_cubic_metre"
      },
      "description": "Коррекция по концентрация N2O (Q N2O)"
    },
    {
      "browseName": "CH_M52_ACM2::57N2O:57QN2O_CORR_H02",
      "aliasName": "57QN2O_CORR_H02",
      "displayName": "57QN2O_CORR_H02",
      "ownerName": "CH_M52_ACM2",
      "ownerGroup": "CH_M52_ACM2::ValueFromFile",
      "type": "variable.analog",
      "dataType": "Double",
      "hist": true,
      "variableGetType": "valueFromSource",
      "getter": "plugForVariable",
      "valueParams": {
        "engineeringUnitsRange": {
          "low": 0,
          "high": 2000
        },
        "engineeringUnits": "milligram_per_cubic_metre"
      },
      "description": "Коррекция по концентрация N2O (Q N2O)"
    },
    {
      "browseName": "CH_M52_ACM2::57N2O:57QN2O_CORR_H03",
      "aliasName": "57QN2O_CORR_H03",
      "displayName": "57QN2O_CORR_H03",
      "ownerName": "CH_M52_ACM2",
      "ownerGroup": "CH_M52_ACM2::ValueFromFile",
      "type": "variable.analog",
      "dataType": "Double",
      "hist": true,
      "variableGetType": "valueFromSource",
      "getter": "plugForVariable",
      "valueParams": {
        "engineeringUnitsRange": {
          "low": 0,
          "high": 2000
        },
        "engineeringUnits": "milligram_per_cubic_metre"
      },
      "description": "Коррекция по концентрация N2O (Q N2O)"
    },
    {
      "browseName": "CH_M52_ACM2::57N2O:57QN2O_CORR_H04",
      "aliasName": "57QN2O_CORR_H04",
      "displayName": "57QN2O_CORR_H04",
      "ownerName": "CH_M52_ACM2",
      "ownerGroup": "CH_M52_ACM2::ValueFromFile",
      "type": "variable.analog",
      "dataType": "Double",
      "hist": true,
      "variableGetType": "valueFromSource",
      "getter": "plugForVariable",
      "valueParams": {
        "engineeringUnitsRange": {
          "low": 0,
          "high": 2000
        },
        "engineeringUnits": "milligram_per_cubic_metre"
      },
      "description": "Коррекция по концентрация N2O (Q N2O)"
    },
    {
      "browseName": "CH_M52_ACM2::57N2O:57QN2O_CORR_H05",
      "aliasName": "57QN2O_CORR_H05",
      "displayName": "57QN2O_CORR_H05",
      "ownerName": "CH_M52_ACM2",
      "ownerGroup": "CH_M52_ACM2::ValueFromFile",
      "type": "variable.analog",
      "dataType": "Double",
      "hist": true,
      "variableGetType": "valueFromSource",
      "getter": "plugForVariable",
      "valueParams": {
        "engineeringUnitsRange": {
          "low": 0,
          "high": 2000
        },
        "engineeringUnits": "milligram_per_cubic_metre"
      },
      "description": "Коррекция по концентрация N2O (Q N2O)"
    },
    {
      "browseName": "CH_M52_ACM2::57N2O:57QN2O_CORR_H06",
      "aliasName": "57QN2O_CORR_H06",
      "displayName": "57QN2O_CORR_H06",
      "ownerName": "CH_M52_ACM2",
      "ownerGroup": "CH_M52_ACM2::ValueFromFile",
      "type": "variable.analog",
      "dataType": "Double",
      "hist": true,
      "variableGetType": "valueFromSource",
      "getter": "plugForVariable",
      "valueParams": {
        "engineeringUnitsRange": {
          "low": 0,
          "high": 2000
        },
        "engineeringUnits": "milligram_per_cubic_metre"
      },
      "description": "Коррекция по концентрация N2O (Q N2O)"
    },
    {
      "browseName": "CH_M52_ACM2::57N2O:57QN2O_CORR_H07",
      "aliasName": "57QN2O_CORR_H07",
      "displayName": "57QN2O_CORR_H07",
      "ownerName": "CH_M52_ACM2",
      "ownerGroup": "CH_M52_ACM2::ValueFromFile",
      "type": "variable.analog",
      "dataType": "Double",
      "hist": true,
      "variableGetType": "valueFromSource",
      "getter": "plugForVariable",
      "valueParams": {
        "engineeringUnitsRange": {
          "low": 0,
          "high": 2000
        },
        "engineeringUnits": "milligram_per_cubic_metre"
      },
      "description": "Коррекция по концентрация N2O (Q N2O)"
    },
    {
      "browseName": "CH_M52_ACM2::57N2O:57QN2O_CORR_H08",
      "aliasName": "57QN2O_CORR_H08",
      "displayName": "57QN2O_CORR_H08",
      "ownerName": "CH_M52_ACM2",
      "ownerGroup": "CH_M52_ACM2::ValueFromFile",
      "type": "variable.analog",
      "dataType": "Double",
      "hist": true,
      "variableGetType": "valueFromSource",
      "getter": "plugForVariable",
      "valueParams": {
        "engineeringUnitsRange": {
          "low": 0,
          "high": 2000
        },
        "engineeringUnits": "milligram_per_cubic_metre"
      },
      "description": "Коррекция по концентрация N2O (Q N2O)"
    },
    {
      "browseName": "CH_M52_ACM2::57N2O:57QN2O_CORR_H09",
      "aliasName": "57QN2O_CORR_H09",
      "displayName": "57QN2O_CORR_H09",
      "ownerName": "CH_M52_ACM2",
      "ownerGroup": "CH_M52_ACM2::ValueFromFile",
      "type": "variable.analog",
      "dataType": "Double",
      "hist": true,
      "variableGetType": "valueFromSource",
      "getter": "plugForVariable",
      "valueParams": {
        "engineeringUnitsRange": {
          "low": 0,
          "high": 2000
        },
        "engineeringUnits": "milligram_per_cubic_metre"
      },
      "description": "Коррекция по концентрация N2O (Q N2O)"
    },
    {
      "browseName": "CH_M52_ACM2::57N2O:57QN2O_CORR_H10",
      "aliasName": "57QN2O_CORR_H10",
      "displayName": "57QN2O_CORR_H10",
      "ownerName": "CH_M52_ACM2",
      "ownerGroup": "CH_M52_ACM2::ValueFromFile",
      "type": "variable.analog",
      "dataType": "Double",
      "hist": true,
      "variableGetType": "valueFromSource",
      "getter": "plugForVariable",
      "valueParams": {
        "engineeringUnitsRange": {
          "low": 0,
          "high": 2000
        },
        "engineeringUnits": "milligram_per_cubic_metre"
      },
      "description": "Коррекция по концентрация N2O (Q N2O)"
    },
    {
      "browseName": "CH_M52_ACM2::57N2O:57QN2O_CORR_H11",
      "aliasName": "57QN2O_CORR_H11",
      "displayName": "57QN2O_CORR_H11",
      "ownerName": "CH_M52_ACM2",
      "ownerGroup": "CH_M52_ACM2::ValueFromFile",
      "type": "variable.analog",
      "dataType": "Double",
      "hist": true,
      "variableGetType": "valueFromSource",
      "getter": "plugForVariable",
      "valueParams": {
        "engineeringUnitsRange": {
          "low": 0,
          "high": 2000
        },
        "engineeringUnits": "milligram_per_cubic_metre"
      },
      "description": "Коррекция по концентрация N2O (Q N2O)"
    },
    {
      "browseName": "CH_M52_ACM2::57N2O:57QN2O_CORR_H12",
      "aliasName": "57QN2O_CORR_H12",
      "displayName": "57QN2O_CORR_H12",
      "ownerName": "CH_M52_ACM2",
      "ownerGroup": "CH_M52_ACM2::ValueFromFile",
      "type": "variable.analog",
      "dataType": "Double",
      "hist": true,
      "variableGetType": "valueFromSource",
      "getter": "plugForVariable",
      "valueParams": {
        "engineeringUnitsRange": {
          "low": 0,
          "high": 2000
        },
        "engineeringUnits": "milligram_per_cubic_metre"
      },
      "description": "Коррекция по концентрация N2O (Q N2O)"
    },
    {
      "browseName": "CH_M52_ACM2::57N2O:57QN2O_CORR_H13",
      "aliasName": "57QN2O_CORR_H13",
      "displayName": "57QN2O_CORR_H13",
      "ownerName": "CH_M52_ACM2",
      "ownerGroup": "CH_M52_ACM2::ValueFromFile",
      "type": "variable.analog",
      "dataType": "Double",
      "hist": true,
      "variableGetType": "valueFromSource",
      "getter": "plugForVariable",
      "valueParams": {
        "engineeringUnitsRange": {
          "low": 0,
          "high": 2000
        },
        "engineeringUnits": "milligram_per_cubic_metre"
      },
      "description": "Коррекция по концентрация N2O (Q N2O)"
    },
    {
      "browseName": "CH_M52_ACM2::57N2O:57QN2O_CORR_H14",
      "aliasName": "57QN2O_CORR_H14",
      "displayName": "57QN2O_CORR_H14",
      "ownerName": "CH_M52_ACM2",
      "ownerGroup": "CH_M52_ACM2::ValueFromFile",
      "type": "variable.analog",
      "dataType": "Double",
      "hist": true,
      "variableGetType": "valueFromSource",
      "getter": "plugForVariable",
      "valueParams": {
        "engineeringUnitsRange": {
          "low": 0,
          "high": 2000
        },
        "engineeringUnits": "milligram_per_cubic_metre"
      },
      "description": "Коррекция по концентрация N2O (Q N2O)"
    },
    {
      "browseName": "CH_M52_ACM2::57N2O:57QN2O_CORR_H15",
      "aliasName": "57QN2O_CORR_H15",
      "displayName": "57QN2O_CORR_H15",
      "ownerName": "CH_M52_ACM2",
      "ownerGroup": "CH_M52_ACM2::ValueFromFile",
      "type": "variable.analog",
      "dataType": "Double",
      "hist": true,
      "variableGetType": "valueFromSource",
      "getter": "plugForVariable",
      "valueParams": {
        "engineeringUnitsRange": {
          "low": 0,
          "high": 2000
        },
        "engineeringUnits": "milligram_per_cubic_metre"
      },
      "description": "Коррекция по концентрация N2O (Q N2O)"
    },
    {
      "browseName": "CH_M52_ACM2::57N2O:57QN2O_CORR_H16",
      "aliasName": "57QN2O_CORR_H16",
      "displayName": "57QN2O_CORR_H16",
      "ownerName": "CH_M52_ACM2",
      "ownerGroup": "CH_M52_ACM2::ValueFromFile",
      "type": "variable.analog",
      "dataType": "Double",
      "hist": true,
      "variableGetType": "valueFromSource",
      "getter": "plugForVariable",
      "valueParams": {
        "engineeringUnitsRange": {
          "low": 0,
          "high": 2000
        },
        "engineeringUnits": "milligram_per_cubic_metre"
      },
      "description": "Коррекция по концентрация N2O (Q N2O)"
    },
    {
      "browseName": "CH_M52_ACM2::57N2O:57QN2O_CORR_H17",
      "aliasName": "57QN2O_CORR_H17",
      "displayName": "57QN2O_CORR_H17",
      "ownerName": "CH_M52_ACM2",
      "ownerGroup": "CH_M52_ACM2::ValueFromFile",
      "type": "variable.analog",
      "dataType": "Double",
      "hist": true,
      "variableGetType": "valueFromSource",
      "getter": "plugForVariable",
      "valueParams": {
        "engineeringUnitsRange": {
          "low": 0,
          "high": 2000
        },
        "engineeringUnits": "milligram_per_cubic_metre"
      },
      "description": "Коррекция по концентрация N2O (Q N2O)"
    },
    {
      "browseName": "CH_M52_ACM2::57N2O:57QN2O_CORR_H18",
      "aliasName": "57QN2O_CORR_H18",
      "displayName": "57QN2O_CORR_H18",
      "ownerName": "CH_M52_ACM2",
      "ownerGroup": "CH_M52_ACM2::ValueFromFile",
      "type": "variable.analog",
      "dataType": "Double",
      "hist": true,
      "variableGetType": "valueFromSource",
      "getter": "plugForVariable",
      "valueParams": {
        "engineeringUnitsRange": {
          "low": 0,
          "high": 2000
        },
        "engineeringUnits": "milligram_per_cubic_metre"
      },
      "description": "Коррекция по концентрация N2O (Q N2O)"
    },
    {
      "browseName": "CH_M52_ACM2::57N2O:57QN2O_CORR_H19",
      "aliasName": "57QN2O_CORR_H19",
      "displayName": "57QN2O_CORR_H19",
      "ownerName": "CH_M52_ACM2",
      "ownerGroup": "CH_M52_ACM2::ValueFromFile",
      "type": "variable.analog",
      "dataType": "Double",
      "hist": true,
      "variableGetType": "valueFromSource",
      "getter": "plugForVariable",
      "valueParams": {
        "engineeringUnitsRange": {
          "low": 0,
          "high": 2000
        },
        "engineeringUnits": "milligram_per_cubic_metre"
      },
      "description": "Коррекция по концентрация N2O (Q N2O)"
    },
    {
      "browseName": "CH_M52_ACM2::57N2O:57QN2O_CORR_H20",
      "aliasName": "57QN2O_CORR_H20",
      "displayName": "57QN2O_CORR_H20",
      "ownerName": "CH_M52_ACM2",
      "ownerGroup": "CH_M52_ACM2::ValueFromFile",
      "type": "variable.analog",
      "dataType": "Double",
      "hist": true,
      "variableGetType": "valueFromSource",
      "getter": "plugForVariable",
      "valueParams": {
        "engineeringUnitsRange": {
          "low": 0,
          "high": 2000
        },
        "engineeringUnits": "milligram_per_cubic_metre"
      },
      "description": "Коррекция по концентрация N2O (Q N2O)"
    },
    {
      "browseName": "CH_M52_ACM2::57N2O:57QN2O_CORR_H21",
      "aliasName": "57QN2O_CORR_H21",
      "displayName": "57QN2O_CORR_H21",
      "ownerName": "CH_M52_ACM2",
      "ownerGroup": "CH_M52_ACM2::ValueFromFile",
      "type": "variable.analog",
      "dataType": "Double",
      "hist": true,
      "variableGetType": "valueFromSource",
      "getter": "plugForVariable",
      "valueParams": {
        "engineeringUnitsRange": {
          "low": 0,
          "high": 2000
        },
        "engineeringUnits": "milligram_per_cubic_metre"
      },
      "description": "Коррекция по концентрация N2O (Q N2O)"
    },
    {
      "browseName": "CH_M52_ACM2::57N2O:57QN2O_CORR_H22",
      "aliasName": "57QN2O_CORR_H22",
      "displayName": "57QN2O_CORR_H22",
      "ownerName": "CH_M52_ACM2",
      "ownerGroup": "CH_M52_ACM2::ValueFromFile",
      "type": "variable.analog",
      "dataType": "Double",
      "hist": true,
      "variableGetType": "valueFromSource",
      "getter": "plugForVariable",
      "valueParams": {
        "engineeringUnitsRange": {
          "low": 0,
          "high": 2000
        },
        "engineeringUnits": "milligram_per_cubic_metre"
      },
      "description": "Коррекция по концентрация N2O (Q N2O)"
    },
    {
      "browseName": "CH_M52_ACM2::57N2O:57QN2O_CORR_H23",
      "aliasName": "57QN2O_CORR_H23",
      "displayName": "57QN2O_CORR_H23",
      "ownerName": "CH_M52_ACM2",
      "ownerGroup": "CH_M52_ACM2::ValueFromFile",
      "type": "variable.analog",
      "dataType": "Double",
      "hist": true,
      "variableGetType": "valueFromSource",
      "getter": "plugForVariable",
      "valueParams": {
        "engineeringUnitsRange": {
          "low": 0,
          "high": 2000
        },
        "engineeringUnits": "milligram_per_cubic_metre"
      },
      "description": "Коррекция по концентрация N2O (Q N2O)"
    },
    {
      "browseName": "CH_M52_ACM2::57N2O:57QN2O_CORR_H24",
      "aliasName": "57QN2O_CORR_H24",
      "displayName": "57QN2O_CORR_H24",
      "ownerName": "CH_M52_ACM2",
      "ownerGroup": "CH_M52_ACM2::ValueFromFile",
      "type": "variable.analog",
      "dataType": "Double",
      "hist": true,
      "variableGetType": "valueFromSource",
      "getter": "plugForVariable",
      "valueParams": {
        "engineeringUnitsRange": {
          "low": 0,
          "high": 2000
        },
        "engineeringUnits": "milligram_per_cubic_metre"
      },
      "description": "Коррекция по концентрация N2O (Q N2O)"
    },
    {
      "browseName": "CH_M52_ACM2::57VSG:57FVSG_CORR_H01",
      "aliasName": "57FVSG_CORR_H01",
      "displayName": "57FVSG_CORR_H01",
      "ownerName": "CH_M52_ACM2",
      "ownerGroup": "CH_M52_ACM2::ValueFromFile",
      "type": "variable.analog",
      "dataType": "Double",
      "hist": true,
      "variableGetType": "valueFromSource",
      "getter": "plugForVariable",
      "valueParams": {
        "engineeringUnitsRange": {
          "low": 0,
          "high": 900000
        },
        "engineeringUnits": "cubic_metre_per_hour"
      },
      "description": "Коррекция по расходу выхл. газов (F VSG)"
    },
    {
      "browseName": "CH_M52_ACM2::57VSG:57FVSG_CORR_H02",
      "aliasName": "57FVSG_CORR_H02",
      "displayName": "57FVSG_CORR_H02",
      "ownerName": "CH_M52_ACM2",
      "ownerGroup": "CH_M52_ACM2::ValueFromFile",
      "type": "variable.analog",
      "dataType": "Double",
      "hist": true,
      "variableGetType": "valueFromSource",
      "getter": "plugForVariable",
      "valueParams": {
        "engineeringUnitsRange": {
          "low": 0,
          "high": 900000
        },
        "engineeringUnits": "cubic_metre_per_hour"
      },
      "description": "Коррекция по расходу выхл. газов (F VSG)"
    },
    {
      "browseName": "CH_M52_ACM2::57VSG:57FVSG_CORR_H03",
      "aliasName": "57FVSG_CORR_H03",
      "displayName": "57FVSG_CORR_H03",
      "ownerName": "CH_M52_ACM2",
      "ownerGroup": "CH_M52_ACM2::ValueFromFile",
      "type": "variable.analog",
      "dataType": "Double",
      "hist": true,
      "variableGetType": "valueFromSource",
      "getter": "plugForVariable",
      "valueParams": {
        "engineeringUnitsRange": {
          "low": 0,
          "high": 900000
        },
        "engineeringUnits": "cubic_metre_per_hour"
      },
      "description": "Коррекция по расходу выхл. газов (F VSG)"
    },
    {
      "browseName": "CH_M52_ACM2::57VSG:57FVSG_CORR_H04",
      "aliasName": "57FVSG_CORR_H04",
      "displayName": "57FVSG_CORR_H04",
      "ownerName": "CH_M52_ACM2",
      "ownerGroup": "CH_M52_ACM2::ValueFromFile",
      "type": "variable.analog",
      "dataType": "Double",
      "hist": true,
      "variableGetType": "valueFromSource",
      "getter": "plugForVariable",
      "valueParams": {
        "engineeringUnitsRange": {
          "low": 0,
          "high": 900000
        },
        "engineeringUnits": "cubic_metre_per_hour"
      },
      "description": "Коррекция по расходу выхл. газов (F VSG)"
    },
    {
      "browseName": "CH_M52_ACM2::57VSG:57FVSG_CORR_H05",
      "aliasName": "57FVSG_CORR_H05",
      "displayName": "57FVSG_CORR_H05",
      "ownerName": "CH_M52_ACM2",
      "ownerGroup": "CH_M52_ACM2::ValueFromFile",
      "type": "variable.analog",
      "dataType": "Double",
      "hist": true,
      "variableGetType": "valueFromSource",
      "getter": "plugForVariable",
      "valueParams": {
        "engineeringUnitsRange": {
          "low": 0,
          "high": 900000
        },
        "engineeringUnits": "cubic_metre_per_hour"
      },
      "description": "Коррекция по расходу выхл. газов (F VSG)"
    },
    {
      "browseName": "CH_M52_ACM2::57VSG:57FVSG_CORR_H06",
      "aliasName": "57FVSG_CORR_H06",
      "displayName": "57FVSG_CORR_H06",
      "ownerName": "CH_M52_ACM2",
      "ownerGroup": "CH_M52_ACM2::ValueFromFile",
      "type": "variable.analog",
      "dataType": "Double",
      "hist": true,
      "variableGetType": "valueFromSource",
      "getter": "plugForVariable",
      "valueParams": {
        "engineeringUnitsRange": {
          "low": 0,
          "high": 900000
        },
        "engineeringUnits": "cubic_metre_per_hour"
      },
      "description": "Коррекция по расходу выхл. газов (F VSG)"
    },
    {
      "browseName": "CH_M52_ACM2::57VSG:57FVSG_CORR_H07",
      "aliasName": "57FVSG_CORR_H07",
      "displayName": "57FVSG_CORR_H07",
      "ownerName": "CH_M52_ACM2",
      "ownerGroup": "CH_M52_ACM2::ValueFromFile",
      "type": "variable.analog",
      "dataType": "Double",
      "hist": true,
      "variableGetType": "valueFromSource",
      "getter": "plugForVariable",
      "valueParams": {
        "engineeringUnitsRange": {
          "low": 0,
          "high": 900000
        },
        "engineeringUnits": "cubic_metre_per_hour"
      },
      "description": "Коррекция по расходу выхл. газов (F VSG)"
    },
    {
      "browseName": "CH_M52_ACM2::57VSG:57FVSG_CORR_H08",
      "aliasName": "57FVSG_CORR_H08",
      "displayName": "57FVSG_CORR_H08",
      "ownerName": "CH_M52_ACM2",
      "ownerGroup": "CH_M52_ACM2::ValueFromFile",
      "type": "variable.analog",
      "dataType": "Double",
      "hist": true,
      "variableGetType": "valueFromSource",
      "getter": "plugForVariable",
      "valueParams": {
        "engineeringUnitsRange": {
          "low": 0,
          "high": 900000
        },
        "engineeringUnits": "cubic_metre_per_hour"
      },
      "description": "Коррекция по расходу выхл. газов (F VSG)"
    },
    {
      "browseName": "CH_M52_ACM2::57VSG:57FVSG_CORR_H09",
      "aliasName": "57FVSG_CORR_H09",
      "displayName": "57FVSG_CORR_H09",
      "ownerName": "CH_M52_ACM2",
      "ownerGroup": "CH_M52_ACM2::ValueFromFile",
      "type": "variable.analog",
      "dataType": "Double",
      "hist": true,
      "variableGetType": "valueFromSource",
      "getter": "plugForVariable",
      "valueParams": {
        "engineeringUnitsRange": {
          "low": 0,
          "high": 900000
        },
        "engineeringUnits": "cubic_metre_per_hour"
      },
      "description": "Коррекция по расходу выхл. газов (F VSG)"
    },
    {
      "browseName": "CH_M52_ACM2::57VSG:57FVSG_CORR_H10",
      "aliasName": "57FVSG_CORR_H10",
      "displayName": "57FVSG_CORR_H10",
      "ownerName": "CH_M52_ACM2",
      "ownerGroup": "CH_M52_ACM2::ValueFromFile",
      "type": "variable.analog",
      "dataType": "Double",
      "hist": true,
      "variableGetType": "valueFromSource",
      "getter": "plugForVariable",
      "valueParams": {
        "engineeringUnitsRange": {
          "low": 0,
          "high": 900000
        },
        "engineeringUnits": "cubic_metre_per_hour"
      },
      "description": "Коррекция по расходу выхл. газов (F VSG)"
    },
    {
      "browseName": "CH_M52_ACM2::57VSG:57FVSG_CORR_H11",
      "aliasName": "57FVSG_CORR_H11",
      "displayName": "57FVSG_CORR_H11",
      "ownerName": "CH_M52_ACM2",
      "ownerGroup": "CH_M52_ACM2::ValueFromFile",
      "type": "variable.analog",
      "dataType": "Double",
      "hist": true,
      "variableGetType": "valueFromSource",
      "getter": "plugForVariable",
      "valueParams": {
        "engineeringUnitsRange": {
          "low": 0,
          "high": 900000
        },
        "engineeringUnits": "cubic_metre_per_hour"
      },
      "description": "Коррекция по расходу выхл. газов (F VSG)"
    },
    {
      "browseName": "CH_M52_ACM2::57VSG:57FVSG_CORR_H12",
      "aliasName": "57FVSG_CORR_H12",
      "displayName": "57FVSG_CORR_H12",
      "ownerName": "CH_M52_ACM2",
      "ownerGroup": "CH_M52_ACM2::ValueFromFile",
      "type": "variable.analog",
      "dataType": "Double",
      "hist": true,
      "variableGetType": "valueFromSource",
      "getter": "plugForVariable",
      "valueParams": {
        "engineeringUnitsRange": {
          "low": 0,
          "high": 900000
        },
        "engineeringUnits": "cubic_metre_per_hour"
      },
      "description": "Коррекция по расходу выхл. газов (F VSG)"
    },
    {
      "browseName": "CH_M52_ACM2::57VSG:57FVSG_CORR_H13",
      "aliasName": "57FVSG_CORR_H13",
      "displayName": "57FVSG_CORR_H13",
      "ownerName": "CH_M52_ACM2",
      "ownerGroup": "CH_M52_ACM2::ValueFromFile",
      "type": "variable.analog",
      "dataType": "Double",
      "hist": true,
      "variableGetType": "valueFromSource",
      "getter": "plugForVariable",
      "valueParams": {
        "engineeringUnitsRange": {
          "low": 0,
          "high": 900000
        },
        "engineeringUnits": "cubic_metre_per_hour"
      },
      "description": "Коррекция по расходу выхл. газов (F VSG)"
    },
    {
      "browseName": "CH_M52_ACM2::57VSG:57FVSG_CORR_H14",
      "aliasName": "57FVSG_CORR_H14",
      "displayName": "57FVSG_CORR_H14",
      "ownerName": "CH_M52_ACM2",
      "ownerGroup": "CH_M52_ACM2::ValueFromFile",
      "type": "variable.analog",
      "dataType": "Double",
      "hist": true,
      "variableGetType": "valueFromSource",
      "getter": "plugForVariable",
      "valueParams": {
        "engineeringUnitsRange": {
          "low": 0,
          "high": 900000
        },
        "engineeringUnits": "cubic_metre_per_hour"
      },
      "description": "Коррекция по расходу выхл. газов (F VSG)"
    },
    {
      "browseName": "CH_M52_ACM2::57VSG:57FVSG_CORR_H15",
      "aliasName": "57FVSG_CORR_H15",
      "displayName": "57FVSG_CORR_H15",
      "ownerName": "CH_M52_ACM2",
      "ownerGroup": "CH_M52_ACM2::ValueFromFile",
      "type": "variable.analog",
      "dataType": "Double",
      "hist": true,
      "variableGetType": "valueFromSource",
      "getter": "plugForVariable",
      "valueParams": {
        "engineeringUnitsRange": {
          "low": 0,
          "high": 900000
        },
        "engineeringUnits": "cubic_metre_per_hour"
      },
      "description": "Коррекция по расходу выхл. газов (F VSG)"
    },
    {
      "browseName": "CH_M52_ACM2::57VSG:57FVSG_CORR_H16",
      "aliasName": "57FVSG_CORR_H16",
      "displayName": "57FVSG_CORR_H16",
      "ownerName": "CH_M52_ACM2",
      "ownerGroup": "CH_M52_ACM2::ValueFromFile",
      "type": "variable.analog",
      "dataType": "Double",
      "hist": true,
      "variableGetType": "valueFromSource",
      "getter": "plugForVariable",
      "valueParams": {
        "engineeringUnitsRange": {
          "low": 0,
          "high": 900000
        },
        "engineeringUnits": "cubic_metre_per_hour"
      },
      "description": "Коррекция по расходу выхл. газов (F VSG)"
    },
    {
      "browseName": "CH_M52_ACM2::57VSG:57FVSG_CORR_H17",
      "aliasName": "57FVSG_CORR_H17",
      "displayName": "57FVSG_CORR_H17",
      "ownerName": "CH_M52_ACM2",
      "ownerGroup": "CH_M52_ACM2::ValueFromFile",
      "type": "variable.analog",
      "dataType": "Double",
      "hist": true,
      "variableGetType": "valueFromSource",
      "getter": "plugForVariable",
      "valueParams": {
        "engineeringUnitsRange": {
          "low": 0,
          "high": 900000
        },
        "engineeringUnits": "cubic_metre_per_hour"
      },
      "description": "Коррекция по расходу выхл. газов (F VSG)"
    },
    {
      "browseName": "CH_M52_ACM2::57VSG:57FVSG_CORR_H18",
      "aliasName": "57FVSG_CORR_H18",
      "displayName": "57FVSG_CORR_H18",
      "ownerName": "CH_M52_ACM2",
      "ownerGroup": "CH_M52_ACM2::ValueFromFile",
      "type": "variable.analog",
      "dataType": "Double",
      "hist": true,
      "variableGetType": "valueFromSource",
      "getter": "plugForVariable",
      "valueParams": {
        "engineeringUnitsRange": {
          "low": 0,
          "high": 900000
        },
        "engineeringUnits": "cubic_metre_per_hour"
      },
      "description": "Коррекция по расходу выхл. газов (F VSG)"
    },
    {
      "browseName": "CH_M52_ACM2::57VSG:57FVSG_CORR_H19",
      "aliasName": "57FVSG_CORR_H19",
      "displayName": "57FVSG_CORR_H19",
      "ownerName": "CH_M52_ACM2",
      "ownerGroup": "CH_M52_ACM2::ValueFromFile",
      "type": "variable.analog",
      "dataType": "Double",
      "hist": true,
      "variableGetType": "valueFromSource",
      "getter": "plugForVariable",
      "valueParams": {
        "engineeringUnitsRange": {
          "low": 0,
          "high": 900000
        },
        "engineeringUnits": "cubic_metre_per_hour"
      },
      "description": "Коррекция по расходу выхл. газов (F VSG)"
    },
    {
      "browseName": "CH_M52_ACM2::57VSG:57FVSG_CORR_H20",
      "aliasName": "57FVSG_CORR_H20",
      "displayName": "57FVSG_CORR_H20",
      "ownerName": "CH_M52_ACM2",
      "ownerGroup": "CH_M52_ACM2::ValueFromFile",
      "type": "variable.analog",
      "dataType": "Double",
      "hist": true,
      "variableGetType": "valueFromSource",
      "getter": "plugForVariable",
      "valueParams": {
        "engineeringUnitsRange": {
          "low": 0,
          "high": 900000
        },
        "engineeringUnits": "cubic_metre_per_hour"
      },
      "description": "Коррекция по расходу выхл. газов (F VSG)"
    },
    {
      "browseName": "CH_M52_ACM2::57VSG:57FVSG_CORR_H21",
      "aliasName": "57FVSG_CORR_H21",
      "displayName": "57FVSG_CORR_H21",
      "ownerName": "CH_M52_ACM2",
      "ownerGroup": "CH_M52_ACM2::ValueFromFile",
      "type": "variable.analog",
      "dataType": "Double",
      "hist": true,
      "variableGetType": "valueFromSource",
      "getter": "plugForVariable",
      "valueParams": {
        "engineeringUnitsRange": {
          "low": 0,
          "high": 900000
        },
        "engineeringUnits": "cubic_metre_per_hour"
      },
      "description": "Коррекция по расходу выхл. газов (F VSG)"
    },
    {
      "browseName": "CH_M52_ACM2::57VSG:57FVSG_CORR_H22",
      "aliasName": "57FVSG_CORR_H22",
      "displayName": "57FVSG_CORR_H22",
      "ownerName": "CH_M52_ACM2",
      "ownerGroup": "CH_M52_ACM2::ValueFromFile",
      "type": "variable.analog",
      "dataType": "Double",
      "hist": true,
      "variableGetType": "valueFromSource",
      "getter": "plugForVariable",
      "valueParams": {
        "engineeringUnitsRange": {
          "low": 0,
          "high": 900000
        },
        "engineeringUnits": "cubic_metre_per_hour"
      },
      "description": "Коррекция по расходу выхл. газов (F VSG)"
    },
    {
      "browseName": "CH_M52_ACM2::57VSG:57FVSG_CORR_H23",
      "aliasName": "57FVSG_CORR_H23",
      "displayName": "57FVSG_CORR_H23",
      "ownerName": "CH_M52_ACM2",
      "ownerGroup": "CH_M52_ACM2::ValueFromFile",
      "type": "variable.analog",
      "dataType": "Double",
      "hist": true,
      "variableGetType": "valueFromSource",
      "getter": "plugForVariable",
      "valueParams": {
        "engineeringUnitsRange": {
          "low": 0,
          "high": 900000
        },
        "engineeringUnits": "cubic_metre_per_hour"
      },
      "description": "Коррекция по расходу выхл. газов (F VSG)"
    },
    {
      "browseName": "CH_M52_ACM2::57VSG:57FVSG_CORR_H24",
      "aliasName": "57FVSG_CORR_H24",
      "displayName": "57FVSG_CORR_H24",
      "ownerName": "CH_M52_ACM2",
      "ownerGroup": "CH_M52_ACM2::ValueFromFile",
      "type": "variable.analog",
      "dataType": "Double",
      "hist": true,
      "variableGetType": "valueFromSource",
      "getter": "plugForVariable",
      "valueParams": {
        "engineeringUnitsRange": {
          "low": 0,
          "high": 900000
        },
        "engineeringUnits": "cubic_metre_per_hour"
      },
      "description": "Коррекция по расходу выхл. газов (F VSG)"
    },
    {
      "browseName": "CH_M52_ACM2::57HNO3:57F105_IS_H01",
      "aliasName": "57F105_IS_H01",
      "displayName": "57F105_IS_H01",
      "ownerName": "CH_M52_ACM2",
      "ownerGroup": "CH_M52_ACM2::ValueFromFile",
      "type": "variable.boolean",
      "dataType": "Boolean",
      "hist": true,
      "variableGetType": "valueFromSource",
      "getter": "plugForVariable",
      "description": "Наличие расходов HNO3 (Is F105)"
    },
    {
      "browseName": "CH_M52_ACM2::57HNO3:57F105_IS_H02",
      "aliasName": "57F105_IS_H02",
      "displayName": "57F105_IS_H02",
      "ownerName": "CH_M52_ACM2",
      "ownerGroup": "CH_M52_ACM2::ValueFromFile",
      "type": "variable.boolean",
      "dataType": "Boolean",
      "hist": true,
      "variableGetType": "valueFromSource",
      "getter": "plugForVariable",
      "description": "Наличие расходов HNO3 (Is F105)"
    },
    {
      "browseName": "CH_M52_ACM2::57HNO3:57F105_IS_H03",
      "aliasName": "57F105_IS_H03",
      "displayName": "57F105_IS_H03",
      "ownerName": "CH_M52_ACM2",
      "ownerGroup": "CH_M52_ACM2::ValueFromFile",
      "type": "variable.boolean",
      "dataType": "Boolean",
      "hist": true,
      "variableGetType": "valueFromSource",
      "getter": "plugForVariable",
      "description": "Наличие расходов HNO3 (Is F105)"
    },
    {
      "browseName": "CH_M52_ACM2::57HNO3:57F105_IS_H04",
      "aliasName": "57F105_IS_H04",
      "displayName": "57F105_IS_H04",
      "ownerName": "CH_M52_ACM2",
      "ownerGroup": "CH_M52_ACM2::ValueFromFile",
      "type": "variable.boolean",
      "dataType": "Boolean",
      "hist": true,
      "variableGetType": "valueFromSource",
      "getter": "plugForVariable",
      "description": "Наличие расходов HNO3 (Is F105)"
    },
    {
      "browseName": "CH_M52_ACM2::57HNO3:57F105_IS_H05",
      "aliasName": "57F105_IS_H05",
      "displayName": "57F105_IS_H05",
      "ownerName": "CH_M52_ACM2",
      "ownerGroup": "CH_M52_ACM2::ValueFromFile",
      "type": "variable.boolean",
      "dataType": "Boolean",
      "hist": true,
      "variableGetType": "valueFromSource",
      "getter": "plugForVariable",
      "description": "Наличие расходов HNO3 (Is F105)"
    },
    {
      "browseName": "CH_M52_ACM2::57HNO3:57F105_IS_H06",
      "aliasName": "57F105_IS_H06",
      "displayName": "57F105_IS_H06",
      "ownerName": "CH_M52_ACM2",
      "ownerGroup": "CH_M52_ACM2::ValueFromFile",
      "type": "variable.boolean",
      "dataType": "Boolean",
      "hist": true,
      "variableGetType": "valueFromSource",
      "getter": "plugForVariable",
      "description": "Наличие расходов HNO3 (Is F105)"
    },
    {
      "browseName": "CH_M52_ACM2::57HNO3:57F105_IS_H07",
      "aliasName": "57F105_IS_H07",
      "displayName": "57F105_IS_H07",
      "ownerName": "CH_M52_ACM2",
      "ownerGroup": "CH_M52_ACM2::ValueFromFile",
      "type": "variable.boolean",
      "dataType": "Boolean",
      "hist": true,
      "variableGetType": "valueFromSource",
      "getter": "plugForVariable",
      "description": "Наличие расходов HNO3 (Is F105)"
    },
    {
      "browseName": "CH_M52_ACM2::57HNO3:57F105_IS_H08",
      "aliasName": "57F105_IS_H08",
      "displayName": "57F105_IS_H08",
      "ownerName": "CH_M52_ACM2",
      "ownerGroup": "CH_M52_ACM2::ValueFromFile",
      "type": "variable.boolean",
      "dataType": "Boolean",
      "hist": true,
      "variableGetType": "valueFromSource",
      "getter": "plugForVariable",
      "description": "Наличие расходов HNO3 (Is F105)"
    },
    {
      "browseName": "CH_M52_ACM2::57HNO3:57F105_IS_H09",
      "aliasName": "57F105_IS_H09",
      "displayName": "57F105_IS_H09",
      "ownerName": "CH_M52_ACM2",
      "ownerGroup": "CH_M52_ACM2::ValueFromFile",
      "type": "variable.boolean",
      "dataType": "Boolean",
      "hist": true,
      "variableGetType": "valueFromSource",
      "getter": "plugForVariable",
      "description": "Наличие расходов HNO3 (Is F105)"
    },
    {
      "browseName": "CH_M52_ACM2::57HNO3:57F105_IS_H10",
      "aliasName": "57F105_IS_H10",
      "displayName": "57F105_IS_H10",
      "ownerName": "CH_M52_ACM2",
      "ownerGroup": "CH_M52_ACM2::ValueFromFile",
      "type": "variable.boolean",
      "dataType": "Boolean",
      "hist": true,
      "variableGetType": "valueFromSource",
      "getter": "plugForVariable",
      "description": "Наличие расходов HNO3 (Is F105)"
    },
    {
      "browseName": "CH_M52_ACM2::57HNO3:57F105_IS_H11",
      "aliasName": "57F105_IS_H11",
      "displayName": "57F105_IS_H11",
      "ownerName": "CH_M52_ACM2",
      "ownerGroup": "CH_M52_ACM2::ValueFromFile",
      "type": "variable.boolean",
      "dataType": "Boolean",
      "hist": true,
      "variableGetType": "valueFromSource",
      "getter": "plugForVariable",
      "description": "Наличие расходов HNO3 (Is F105)"
    },
    {
      "browseName": "CH_M52_ACM2::57HNO3:57F105_IS_H12",
      "aliasName": "57F105_IS_H12",
      "displayName": "57F105_IS_H12",
      "ownerName": "CH_M52_ACM2",
      "ownerGroup": "CH_M52_ACM2::ValueFromFile",
      "type": "variable.boolean",
      "dataType": "Boolean",
      "hist": true,
      "variableGetType": "valueFromSource",
      "getter": "plugForVariable",
      "description": "Наличие расходов HNO3 (Is F105)"
    },
    {
      "browseName": "CH_M52_ACM2::57HNO3:57F105_IS_H13",
      "aliasName": "57F105_IS_H13",
      "displayName": "57F105_IS_H13",
      "ownerName": "CH_M52_ACM2",
      "ownerGroup": "CH_M52_ACM2::ValueFromFile",
      "type": "variable.boolean",
      "dataType": "Boolean",
      "hist": true,
      "variableGetType": "valueFromSource",
      "getter": "plugForVariable",
      "description": "Наличие расходов HNO3 (Is F105)"
    },
    {
      "browseName": "CH_M52_ACM2::57HNO3:57F105_IS_H14",
      "aliasName": "57F105_IS_H14",
      "displayName": "57F105_IS_H14",
      "ownerName": "CH_M52_ACM2",
      "ownerGroup": "CH_M52_ACM2::ValueFromFile",
      "type": "variable.boolean",
      "dataType": "Boolean",
      "hist": true,
      "variableGetType": "valueFromSource",
      "getter": "plugForVariable",
      "description": "Наличие расходов HNO3 (Is F105)"
    },
    {
      "browseName": "CH_M52_ACM2::57HNO3:57F105_IS_H15",
      "aliasName": "57F105_IS_H15",
      "displayName": "57F105_IS_H15",
      "ownerName": "CH_M52_ACM2",
      "ownerGroup": "CH_M52_ACM2::ValueFromFile",
      "type": "variable.boolean",
      "dataType": "Boolean",
      "hist": true,
      "variableGetType": "valueFromSource",
      "getter": "plugForVariable",
      "description": "Наличие расходов HNO3 (Is F105)"
    },
    {
      "browseName": "CH_M52_ACM2::57HNO3:57F105_IS_H16",
      "aliasName": "57F105_IS_H16",
      "displayName": "57F105_IS_H16",
      "ownerName": "CH_M52_ACM2",
      "ownerGroup": "CH_M52_ACM2::ValueFromFile",
      "type": "variable.boolean",
      "dataType": "Boolean",
      "hist": true,
      "variableGetType": "valueFromSource",
      "getter": "plugForVariable",
      "description": "Наличие расходов HNO3 (Is F105)"
    },
    {
      "browseName": "CH_M52_ACM2::57HNO3:57F105_IS_H17",
      "aliasName": "57F105_IS_H17",
      "displayName": "57F105_IS_H17",
      "ownerName": "CH_M52_ACM2",
      "ownerGroup": "CH_M52_ACM2::ValueFromFile",
      "type": "variable.boolean",
      "dataType": "Boolean",
      "hist": true,
      "variableGetType": "valueFromSource",
      "getter": "plugForVariable",
      "description": "Наличие расходов HNO3 (Is F105)"
    },
    {
      "browseName": "CH_M52_ACM2::57HNO3:57F105_IS_H18",
      "aliasName": "57F105_IS_H18",
      "displayName": "57F105_IS_H18",
      "ownerName": "CH_M52_ACM2",
      "ownerGroup": "CH_M52_ACM2::ValueFromFile",
      "type": "variable.boolean",
      "dataType": "Boolean",
      "hist": true,
      "variableGetType": "valueFromSource",
      "getter": "plugForVariable",
      "description": "Наличие расходов HNO3 (Is F105)"
    },
    {
      "browseName": "CH_M52_ACM2::57HNO3:57F105_IS_H19",
      "aliasName": "57F105_IS_H19",
      "displayName": "57F105_IS_H19",
      "ownerName": "CH_M52_ACM2",
      "ownerGroup": "CH_M52_ACM2::ValueFromFile",
      "type": "variable.boolean",
      "dataType": "Boolean",
      "hist": true,
      "variableGetType": "valueFromSource",
      "getter": "plugForVariable",
      "description": "Наличие расходов HNO3 (Is F105)"
    },
    {
      "browseName": "CH_M52_ACM2::57HNO3:57F105_IS_H20",
      "aliasName": "57F105_IS_H20",
      "displayName": "57F105_IS_H20",
      "ownerName": "CH_M52_ACM2",
      "ownerGroup": "CH_M52_ACM2::ValueFromFile",
      "type": "variable.boolean",
      "dataType": "Boolean",
      "hist": true,
      "variableGetType": "valueFromSource",
      "getter": "plugForVariable",
      "description": "Наличие расходов HNO3 (Is F105)"
    },
    {
      "browseName": "CH_M52_ACM2::57HNO3:57F105_IS_H21",
      "aliasName": "57F105_IS_H21",
      "displayName": "57F105_IS_H21",
      "ownerName": "CH_M52_ACM2",
      "ownerGroup": "CH_M52_ACM2::ValueFromFile",
      "type": "variable.boolean",
      "dataType": "Boolean",
      "hist": true,
      "variableGetType": "valueFromSource",
      "getter": "plugForVariable",
      "description": "Наличие расходов HNO3 (Is F105)"
    },
    {
      "browseName": "CH_M52_ACM2::57HNO3:57F105_IS_H22",
      "aliasName": "57F105_IS_H22",
      "displayName": "57F105_IS_H22",
      "ownerName": "CH_M52_ACM2",
      "ownerGroup": "CH_M52_ACM2::ValueFromFile",
      "type": "variable.boolean",
      "dataType": "Boolean",
      "hist": true,
      "variableGetType": "valueFromSource",
      "getter": "plugForVariable",
      "description": "Наличие расходов HNO3 (Is F105)"
    },
    {
      "browseName": "CH_M52_ACM2::57HNO3:57F105_IS_H23",
      "aliasName": "57F105_IS_H23",
      "displayName": "57F105_IS_H23",
      "ownerName": "CH_M52_ACM2",
      "ownerGroup": "CH_M52_ACM2::ValueFromFile",
      "type": "variable.boolean",
      "dataType": "Boolean",
      "hist": true,
      "variableGetType": "valueFromSource",
      "getter": "plugForVariable",
      "description": "Наличие расходов HNO3 (Is F105)"
    },
    {
      "browseName": "CH_M52_ACM2::57HNO3:57F105_IS_H24",
      "aliasName": "57F105_IS_H24",
      "displayName": "57F105_IS_H24",
      "ownerName": "CH_M52_ACM2",
      "ownerGroup": "CH_M52_ACM2::ValueFromFile",
      "type": "variable.boolean",
      "dataType": "Boolean",
      "hist": true,
      "variableGetType": "valueFromSource",
      "getter": "plugForVariable",
      "description": "Наличие расходов HNO3 (Is F105)"
    }
  ],
  "methods": []
}